speex_py-0.2.0.dist-info/METADATA
speex_py-0.2.0.dist-info/WHEEL
speex_py.libs/libspeexdsp-def679f4.so.1
speex_py/__init__.py
speex_py/__init__.pyi
speex_py/py.typed
speex_py/speex_py.abi3.so
speex_py-0.2.0.dist-info/RECORD
